wave_packet_dynamics-2.0.0.dist-info/METADATA
wave_packet_dynamics-2.0.0.dist-info/WHEEL
wave_packet_dynamics-2.0.0.dist-info/entry_points.txt
wave_packet_dynamics/__init__.py
wave_packet_dynamics/__main__.py
wave_packet_dynamics/cli.py
wave_packet_dynamics/grid.py
wave_packet_dynamics/operators.py
wave_packet_dynamics/particles.py
wave_packet_dynamics/potential.py
wave_packet_dynamics/py.typed
wave_packet_dynamics/simulation.py
wave_packet_dynamics/visualization.py
wave_packet_dynamics/wave_function.py
wave_packet_dynamics-2.0.0.dist-info/RECORD
