Metadata-Version: 2.1
Name: wave-packet-dynamics
Version: 2.0.0
Summary: Simulation of quantum dynamics.
Author-Email: Robert Grzonka <robert.grzonka@fau.de>
Maintainer-Email: Robert Grzonka <robert.grzonka@fau.de>
License: BSD-3-Clause
Classifier: Development Status :: 4 - Beta
Classifier: Intended Audience :: Education
Classifier: Intended Audience :: Science/Research
Classifier: License :: OSI Approved :: BSD License
Classifier: Natural Language :: English
Classifier: Operating System :: OS Independent
Classifier: Programming Language :: Python
Classifier: Programming Language :: Python :: 3.11
Classifier: Programming Language :: Python :: 3.12
Classifier: Topic :: Scientific/Engineering
Classifier: Topic :: Scientific/Engineering :: Chemistry
Classifier: Topic :: Scientific/Engineering :: Physics
Classifier: Typing :: Typed
Project-URL: Documentation, https://wave-packet-dynamics.readthedocs.io
Project-URL: Tracker, https://github.com/Rastow/wave-packet-dynamics/issues
Project-URL: Source, https://github.com/Rastow/wave-packet-dynamics
Requires-Python: >=3.11
Requires-Dist: numpy>=2.0.0
Requires-Dist: scipy>=1.14.0
Requires-Dist: matplotlib>=3.9.1
Requires-Dist: click>=8.1.7
